LinkedList/LinkedList.py
LinkedList/__init__.py
Node/Node.py
Node/__init__.py
Stack/Stack.py
Stack/__init__.py
Nodes_dchequer-0.0.2.dist-info/LICENSE
Nodes_dchequer-0.0.2.dist-info/METADATA
Nodes_dchequer-0.0.2.dist-info/WHEEL
Nodes_dchequer-0.0.2.dist-info/top_level.txt
Nodes_dchequer-0.0.2.dist-info/RECORD
