Metadata-Version: 2.1
Name: Nodes-dchequer
Version: 0.0.2
Summary: Custom Node Class and Other Implementations
Home-page: https://github.com/dchequer/Nodes
Author: Diego Chequer
Author-email: millychequer@gmail.com
License: UNKNOWN
Project-URL: Bug Tracker, https://github.com/dchequer/Nodes/issues
Platform: UNKNOWN
Classifier: Programming Language :: Python :: 3
Classifier: License :: OSI Approved :: MIT License
Classifier: Operating System :: OS Independent
Requires-Python: >=3.6
License-File: LICENSE
